pupa/__init__.py
pupa/admin.py
pupa/exceptions.py
pupa/models.py
pupa/settings.py
pupa/cli/__init__.py
pupa/cli/__main__.py
pupa/cli/commands/__init__.py
pupa/cli/commands/base.py
pupa/cli/commands/clean.py
pupa/cli/commands/dbinit.py
pupa/cli/commands/init.py
pupa/cli/commands/party.py
pupa/cli/commands/update.py
pupa/ext/__init__.py
pupa/ext/ansistrm.py
pupa/importers/__init__.py
pupa/importers/base.py
pupa/importers/bills.py
pupa/importers/events.py
pupa/importers/jurisdiction.py
pupa/importers/memberships.py
pupa/importers/organizations.py
pupa/importers/people.py
pupa/importers/posts.py
pupa/importers/vote_events.py
pupa/migrations/0001_initial.py
pupa/migrations/0002_auto_20150906_1458.py
pupa/migrations/0003_auto_20151118_0408.py
pupa/migrations/0004_identifier.py
pupa/migrations/0005_auto_20170522_1935.py
pupa/migrations/0006_identifier_jurisdiction.py
pupa/migrations/0007_sessiondataqualityreport.py
pupa/migrations/__init__.py
pupa/reports/__init__.py
pupa/reports/session.py
pupa/scrape/__init__.py
pupa/scrape/base.py
pupa/scrape/bill.py
pupa/scrape/event.py
pupa/scrape/jurisdiction.py
pupa/scrape/popolo.py
pupa/scrape/vote_event.py
pupa/scrape/schemas/__init__.py
pupa/scrape/schemas/bill.py
pupa/scrape/schemas/common.py
pupa/scrape/schemas/event.py
pupa/scrape/schemas/jurisdiction.py
pupa/scrape/schemas/membership.py
pupa/scrape/schemas/organization.py
pupa/scrape/schemas/person.py
pupa/scrape/schemas/post.py
pupa/scrape/schemas/vote_event.py
pupa/tests/__init__.py
pupa/tests/django_settings.py
pupa/tests/importers/__init__.py
pupa/tests/importers/test_base_importer.py
pupa/tests/importers/test_bill_importer.py
pupa/tests/importers/test_event_importer.py
pupa/tests/importers/test_jurisdiction_importer.py
pupa/tests/importers/test_membership_importer.py
pupa/tests/importers/test_organization_importer.py
pupa/tests/importers/test_people_importer.py
pupa/tests/importers/test_post_importer.py
pupa/tests/importers/test_topsort.py
pupa-0.11.0.dist-info/LICENSE
pupa-0.11.0.dist-info/METADATA
pupa-0.11.0.dist-info/WHEEL
pupa-0.11.0.dist-info/entry_points.txt
pupa-0.11.0.dist-info/top_level.txt
pupa-0.11.0.dist-info/RECORD
