Metadata-Version: 2.1
Name: pupa
Version: 0.11.0
Summary: scraping framework for muncipal data
Home-page: https://github.com/opencivicdata/pupa/
Author: James Turk
Author-email: james@openstates.org
License: BSD
Platform: any
Classifier: Development Status :: 4 - Beta
Classifier: Intended Audience :: Developers
Classifier: License :: OSI Approved :: BSD License
Classifier: Natural Language :: English
Classifier: Operating System :: OS Independent
Classifier: Programming Language :: Python :: 3.5
Classifier: Programming Language :: Python :: 3.6
Classifier: Programming Language :: Python :: 3.7
Classifier: Programming Language :: Python :: 3.8
Classifier: Topic :: Software Development :: Libraries :: Python Modules
Requires-Dist: Django (>=2.2)
Requires-Dist: dj-database-url (>=0.3.0)
Requires-Dist: jsonschema (>=3.0.0)
Requires-Dist: opencivicdata (>=3.3.0)
Requires-Dist: psycopg2-binary
Requires-Dist: pytz
Requires-Dist: scrapelib (>=1.0)
Provides-Extra: dev
Requires-Dist: coverage (<=6.5.0) ; extra == 'dev'
Requires-Dist: coveralls ; extra == 'dev'
Requires-Dist: flake8 ; extra == 'dev'
Requires-Dist: freezegun ; extra == 'dev'
Requires-Dist: mock ; extra == 'dev'
Requires-Dist: pytest-cov ; extra == 'dev'
Requires-Dist: pytest-django ; extra == 'dev'
Requires-Dist: pytest (>=3.6) ; extra == 'dev'
